blizz/__init__.py
blizz/_apply.py
blizz/_bootstrapping.py
blizz/_check.py
blizz/_cli.py
blizz/_constants.py
blizz/_docs.py
blizz/_feature_library.py
blizz/_helpers.py
blizz/_inspect.py
blizz/_primitives.py
blizz/_run_config.py
blizz/_runtime.py
blizz/apply.py
blizz/check.py
blizz/sphinx-base/conf.py
blizz/sphinx-base/index.rst
blizz/sphinx-base/_static/blizz-logo.png
blizz/sphinx-base/_static/pandas.svg
blizz/sphinx-base/_static/pull-request-preview-link.png
blizz/sphinx-base/_templates/custom-template.html
blizz/sphinx-base/features/feature-group-template.rst
blizz/sphinx-base/features/index.rst
blizz/sphinx-base/relations/index.rst
blizz/sphinx-base/relations/relation-template.rst
blizz-0.2.5.dist-info/entry_points.txt
blizz-0.2.5.dist-info/LICENSE
blizz-0.2.5.dist-info/WHEEL
blizz-0.2.5.dist-info/METADATA
blizz-0.2.5.dist-info/RECORD
